django_compile_pyc/__init__.py
django_compile_pyc/django_compile.py
django_compile-0.0.5.dist-info/LICENSE
django_compile-0.0.5.dist-info/METADATA
django_compile-0.0.5.dist-info/WHEEL
django_compile-0.0.5.dist-info/entry_points.txt
django_compile-0.0.5.dist-info/top_level.txt
django_compile-0.0.5.dist-info/RECORD
